{"chunk_definitions":[{"row":40,"row_count":1,"visible":true,"expansion_state":0,"options":{"engine":"r","label":"setup","include":false},"document_id":"21AFC3DC","chunk_id":"csetup_chunk","chunk_label":"setup"},{"row":158,"row_count":1,"visible":true,"expansion_state":0,"options":{"engine":"r","label":"ABTGTinstall","echo":true,"eval":false},"document_id":"21AFC3DC","chunk_id":"cmf4h3codvk3j","chunk_label":"ABTGTinstall"},{"row":218,"row_count":1,"visible":true,"expansion_state":0,"options":{"engine":"r","label":"demo","echo":true,"eval":false},"document_id":"21AFC3DC","chunk_id":"c9ixw3nzs65bb","chunk_label":"demo"}],"doc_write_time":1661988426,"working_dir":null,"default_chunk_options":{"echo":false}}